{
  "index": {
    "title": "Get started",
    "display": "hidden",
    "theme": {
      "breadcrumb": false,
      "footer": true,
      "sidebar": true,
      "toc": false,
      "pagination": false
    }
  },

  "404": {
    "title": "404",
    "display": "hidden",
    "theme": {
      "layout": "full",
      "breadcrumb": false,
      "footer": true,
      "sidebar": true,
      "toc": false,
      "pagination": false
    }
  },

  "500": {
    "title": "500",
    "display": "hidden",
    "theme": {
      "layout": "full",
      "breadcrumb": false,
      "footer": true,
      "sidebar": true,
      "toc": false,
      "pagination": false
    }
  },

  "superchain": {
    "title": "The Superchain",
    "type":"page",
    "theme": {
      "navbar": true,
      "sidebar": true,
      "toc": true,
      "pagination": true
    },
    "display": "children"
  },
  "app-developers": {
    "title": "App Devs",
    "type": "page",
    "theme": {
      "navbar": true,
      "sidebar": true,
      "toc": true,
      "pagination": true
    },
    "display": "children"
  },
  "operators": {
    "title": "Operators",
    "type": "page",
    "theme": {
      "navbar": true,
      "sidebar": true,
      "toc": true,
      "pagination": true
    },
    "display": "children"
  },
  "stack": {
    "title": "OP Stack",
    "type": "page",
    "theme": {
      "navbar": true,
      "sidebar": true,
      "toc": true,
      "pagination": true
    },
    "display": "children"
  },

  "+++ NOTICES": {
    "title": "",
    "type": "separator"
  },
  "--- NOTICES": {
    "title": "NOTICES",
    "type": "separator"
  },
  "notices": {
    "title": "Notices",
    "display": "children"
  },
  "+++ CONNECT": {
    "title": "",
    "type": "separator"
  },
  "--- CONNECT": {
    "title": "CONNECT",
    "type": "separator"
  },
  "connect": {
    "title": "Connect",
    "display": "children"
  }
}
